README.md
setup.cfg
setup.py
linear_congruences_riyadk/__init__.py
linear_congruences_riyadk.egg-info/PKG-INFO
linear_congruences_riyadk.egg-info/SOURCES.txt
linear_congruences_riyadk.egg-info/dependency_links.txt
linear_congruences_riyadk.egg-info/not-zip-safe
linear_congruences_riyadk.egg-info/top_level.txt