Metadata-Version: 1.0
Name: linear-congruences-riyadk
Version: 0.1
Summary: Method of linear congruences!
Home-page: https://github.com/Riyadkutabish
Author: Riyad Kutabish
Author-email: riyad.kutabish@student.ie.edu
License: MIT
Platform: UNKNOWN
